{
  "hash": "4f5a7c31",
  "configHash": "93b10950",
  "lockfileHash": "89166934",
  "browserHash": "4f7a528f",
  "optimized": {
    "vue": {
      "src": "../../node_modules/vue/dist/vue.runtime.esm-bundler.js",
      "file": "vue.js",
      "fileHash": "026a9d33",
      "needsInterop": false
    },
    "pinia": {
      "src": "../../node_modules/pinia/dist/pinia.mjs",
      "file": "pinia.js",
      "fileHash": "b9a79c68",
      "needsInterop": false
    },
    "vue-router": {
      "src": "../../node_modules/vue-router/dist/vue-router.mjs",
      "file": "vue-router.js",
      "fileHash": "11b6882b",
      "needsInterop": false
    }
  },
  "chunks": {
    "chunk-TWFATH4K": {
      "file": "chunk-TWFATH4K.js"
    }
  }
}